aboutsba/__init__.py
aboutsba/about.py
About_SBA-1.0.dist-info/METADATA
About_SBA-1.0.dist-info/WHEEL
About_SBA-1.0.dist-info/top_level.txt
About_SBA-1.0.dist-info/RECORD
