Metadata-Version: 2.1
Name: About_SBA
Version: 1.0
Summary: About SBA
